ModernEnigma/__init__.py
ModernEnigma/enigma.py
modernenigma-0.0.2.dist-info/entry_points.txt
modernenigma-0.0.2.dist-info/LICENSE.txt
modernenigma-0.0.2.dist-info/METADATA
modernenigma-0.0.2.dist-info/WHEEL
modernenigma-0.0.2.dist-info/RECORD
