Metadata-Version: 2.1
Name: modernenigma
Version: 0.0.2
Summary: 
Home-page: https://github.com/KevinFerryJr/ModernEnigma
License: AGPL-3.0-or-later
Author: K. Ferry
Requires-Python: >=3.9,<4.0
Classifier: License :: OSI Approved :: GNU Affero General Public License v3 or later (AGPLv3+)
Classifier: Natural Language :: English
Classifier: Operating System :: OS Independent
Classifier: Programming Language :: Python
Classifier: Programming Language :: Python :: 3
Classifier: Programming Language :: Python :: 3.9
Classifier: Programming Language :: Python :: 3.10
Classifier: Programming Language :: Python :: 3.11
Requires-Dist: click (>=7.1.2,<8.0.0)
Project-URL: Repository, https://pypi.org/project/ModernEnigma/
